django_country2/__init__.py
django_country2/context_processors.py
django_country2/geo.py
django_country2/middleware.py
django_country2/urls.py
django_country2/views.py
django_country2-0.0.8.dist-info/LICENSE
django_country2-0.0.8.dist-info/METADATA
django_country2-0.0.8.dist-info/WHEEL
django_country2-0.0.8.dist-info/top_level.txt
django_country2-0.0.8.dist-info/RECORD
