Metadata-Version: 2.1
Name: django-country2
Version: 0.0.8
Summary: Provides Django middleware that detects a country the request came from.
Home-page: https://github.com/Develatio/django-country2
Author: Develatio Technologies S.L.
Author-email: contacto@develat.io
License: UNKNOWN
Platform: UNKNOWN
Requires-Dist: geoip2 (>=2.9.0)
Requires-Dist: django-countries (>=5.3.3)
